undefined/API.py
undefined/Calculator.py
undefined/GraphGenerator.py
undefined/UDFunction.py
undefined/Utils.py
undefined/__init__.py
undefined/__main__.py
undefined_AD-2.1.2.dist-info/LICENSE
undefined_AD-2.1.2.dist-info/METADATA
undefined_AD-2.1.2.dist-info/WHEEL
undefined_AD-2.1.2.dist-info/top_level.txt
undefined_AD-2.1.2.dist-info/RECORD
