Metadata-Version: 2.1
Name: undefined-AD
Version: 2.1.2
Summary: Auto differetiation library
Home-page: https://github.com/cs107-undefined/cs107-FinalProject
Author: cs107-undefined
Author-email: xinran_tang@g.harvard.edu
License: UNKNOWN
Platform: UNKNOWN
Classifier: Intended Audience :: Developers
Classifier: Programming Language :: Python :: 3
Classifier: License :: OSI Approved :: MIT License
Classifier: Topic :: Software Development :: Libraries :: Python Modules
Requires-Python: >=3.6
License-File: LICENSE
Requires-Dist: numpy (>=1.19.0)
Requires-Dist: networkx (>=2.5.1)
Requires-Dist: matplotlib (>=3.4.3)
Requires-Dist: sphinx (==4.2.0)
Requires-Dist: sphinx-rtd-theme (==1.0.0)
